.DS_Store
zhdate/__init__.py
zhdate-0.1.dist-info/LICENSE
zhdate-0.1.dist-info/METADATA
zhdate-0.1.dist-info/WHEEL
zhdate-0.1.dist-info/top_level.txt
zhdate-0.1.dist-info/RECORD
