Metadata-Version: 2.1
Name: zhdate
Version: 0.1
Summary: A pachage to convert Chinese Lunar Calendar to datetime
Home-page: https://github.com/CutePandaSh/zhdate
Author: PandaWithBeard
Author-email: 9861649@qq.com
License: UNKNOWN
Platform: UNKNOWN
Classifier: Programming Language :: Python :: 3
Classifier: License :: OSI Approved :: GNU General Public License v3 or later (GPLv3+)
Classifier: Operating System :: OS Independent
